shantox/__init__.py
shantox/x_n_equals.py
shntox/__init__.py
shntox/x_n_equals .pyx
shntox/x_n_equals.py
shntox-0.1.9.dist-info/LICENSE.txt
shntox-0.1.9.dist-info/METADATA
shntox-0.1.9.dist-info/WHEEL
shntox-0.1.9.dist-info/top_level.txt
shntox-0.1.9.dist-info/RECORD
