Metadata-Version: 2.2
Name: shntox
Version: 0.1.9
Summary: Algebra library
Author: sahin
License: MIT
Requires-Python: >=3.6
License-File: LICENSE.txt
Dynamic: author
Dynamic: description
Dynamic: description-content-type
Dynamic: license
Dynamic: requires-python
Dynamic: summary
